{"cameraMode":{"drawMode":0,"name":"Shaded","section":"Shading Mode"},"sceneLighting":true,"audioPlay":false,"sceneViewState":{"showFog":true,"showMaterialUpdate":false,"showSkybox":true,"showFlares":true,"showImageEffects":true,"showParticleSystems":true},"in2DMode":false,"pivot":{"x":41.073974609375,"y":-367.451904296875,"z":285.8893737792969},"rotation":{"x":0.4375014901161194,"y":0.10693231225013733,"z":-0.05248824879527092,"w":0.8912928700447083},"size":473.8587951660156,"orthographic":false}